{
  "_format": "hh-sol-cache-2",
  "files": {
    "D:\\Blockchain\\new crowdfunding\\crowdfunding\\contracts\\Campaign.sol": {
      "lastModificationDate": 1684342089466,
      "contentHash": "4c50ef5092518b46ef8e031082154f61",
      "sourceName": "contracts/Campaign.sol",
      "solcConfig": {
        "version": "0.8.10",
        "settings": {
          "optimizer": {
            "enabled": false,
            "runs": 200
          },
          "outputSelection": {
            "*": {
              "*": [
                "abi",
                "evm.bytecode",
                "evm.deployedBytecode",
                "evm.methodIdentifiers",
                "metadata"
              ],
              "": [
                "ast"
              ]
            }
          }
        }
      },
      "imports": [],
      "versionPragmas": [
        "^0.8.0"
      ],
      "artifacts": [
        "CampaignFactory"
      ]
    }
  }
}
